drug_database/__init__.py
drug_database/__main__.py
drug_database/_drug_database.py
drug_database/cli.py
drug_database/drug_factors.json
drug_database-0.1.3.dist-info/LICENSE
drug_database-0.1.3.dist-info/METADATA
drug_database-0.1.3.dist-info/WHEEL
drug_database-0.1.3.dist-info/entry_points.txt
drug_database-0.1.3.dist-info/top_level.txt
drug_database-0.1.3.dist-info/RECORD
