Metadata-Version: 2.1
Name: drug-database
Version: 0.1.3
Summary: Tool for getting scaling factors from different drugs
Author-email: Henrik Finsberg <henriknf@simula.no>
License: Copyright 2022 Henrik Finsberg
License-File: LICENSE
Requires-Dist: typer
Requires-Dist: rich
Provides-Extra: all
Requires-Dist: drug-database[test] ; extra == 'all'
Requires-Dist: drug-database[docs] ; extra == 'all'
Requires-Dist: drug-database[dev] ; extra == 'all'
Provides-Extra: dev
Requires-Dist: pdbpp ; extra == 'dev'
Requires-Dist: ipython ; extra == 'dev'
Requires-Dist: bump2version ; extra == 'dev'
Requires-Dist: pre-commit ; extra == 'dev'
Provides-Extra: docs
Requires-Dist: jupyter-book ; extra == 'docs'
Requires-Dist: jupytext ; extra == 'docs'
Requires-Dist: plotly ; extra == 'docs'
Requires-Dist: ipython (<8.7.0) ; extra == 'docs'
Provides-Extra: test
Requires-Dist: pytest ; extra == 'test'
Requires-Dist: pytest-cov ; extra == 'test'
